cronevents/__init__.py
cronevents/cli.py
cronevents/event.py
cronevents/event_manager.py
cronevents/event_run.py
cronevents/register.py
cronevents/timezone_util.py
cronevents-0.0.39.dist-info/licenses/LICENSE
cronevents-0.0.39.dist-info/METADATA
cronevents-0.0.39.dist-info/WHEEL
cronevents-0.0.39.dist-info/entry_points.txt
cronevents-0.0.39.dist-info/top_level.txt
cronevents-0.0.39.dist-info/RECORD
