Metadata-Version: 2.4
Name: cronevents
Version: 0.0.39
Summary: A package to run cron jobs(events)
Home-page: 
Author: Daniel Olson
Author-email: daniel@orphos.cloud
Keywords: cron jobs
Classifier: Development Status :: 3 - Alpha
Classifier: Intended Audience :: Developers
Classifier: License :: OSI Approved :: MIT License
Classifier: Operating System :: OS Independent
Classifier: Programming Language :: Python :: 3
Classifier: Programming Language :: Python :: 3.10
Classifier: Programming Language :: Python :: 3.11
Classifier: Programming Language :: Python :: 3.12
Requires-Python: >=3.10
License-File: LICENSE
Requires-Dist: psycopg2-binary
Requires-Dist: python-dotenv
Requires-Dist: buelon
Requires-Dist: pexpect
Dynamic: author
Dynamic: author-email
Dynamic: classifier
Dynamic: description
Dynamic: description-content-type
Dynamic: keywords
Dynamic: license-file
Dynamic: requires-dist
Dynamic: requires-python
Dynamic: summary
